peepy/Observables.py
peepy/__init__.py
peepy-0.0.2.dist-info/LICENSE
peepy-0.0.2.dist-info/METADATA
peepy-0.0.2.dist-info/WHEEL
peepy-0.0.2.dist-info/top_level.txt
peepy-0.0.2.dist-info/RECORD
